bisex/__init__.py
bisex/generator.py
bisex/interfaces.py
bisex/py.typed
bisex/static_extract.py
bisex/typescript.py
bisex-0.2.0.dist-info/METADATA
bisex-0.2.0.dist-info/WHEEL
bisex-0.2.0.dist-info/RECORD
