Metadata-Version: 2.4
Name: bisex
Version: 0.2.0
Summary: General‑purpose Python→TypeScript type generator
Project-URL: Homepage, https://github.com/hyvnova/bisex
Author: Hyv
License: MIT
Keywords: ast,codegen,dataclasses,enums,typescript
Classifier: License :: OSI Approved :: MIT License
Classifier: Programming Language :: Python :: 3
Classifier: Topic :: Software Development :: Code Generators
Classifier: Typing :: Typed
Requires-Python: >=3.10
